<?xml version="1.0" encoding="UTF-8"?>
<!DOCTYPE configuremap [
<!ELEMENT configuremap (configure)+>
<!ELEMENT configure (#PCDATA)>
<!ATTLIST configure name CDATA #REQUIRED>
<!ATTLIST configure value CDATA #REQUIRED>
]>
<configuremap>
  <configure name="CC" value="gcc"/>
  <configure name="CFLAGS" value="-L. -Wall -march=penryn -fexceptions -D_FORTIFY_SOURCE=0 -D_THREAD_SAFE -pthread -DMAGICKCORE_HDRI_ENABLE=0 -DMAGICKCORE_QUANTUM_DEPTH=16"/>
  <configure name="CODER_PATH" value=""/>
  <configure name="CONFIGURE_PATH" value=""/>
  <configure name="CONFIGURE" value="./configure '--enable-zero-configuration' '--disable-assert' '--enable-shared=no' '--disable-docs' '--without-perl' '--disable-dependency-tracking' '--enable-delegate-build' '--disable-shared' 'CFLAGS=-L.' 'LIBS=-ljbig -ltiff -ljasper -ljpeg -lpng -lbz2 -lz -lpthread -lm -lfreetype' 'CPPFLAGS=-I.'"/>
  <configure name="COPYRIGHT" value="Copyright (C) 1999-2014 ImageMagick Studio LLC"/>
  <configure name="CPPFLAGS" value="-I."/>
  <configure name="CXXFLAGS" value="-g -O2 -D_THREAD_SAFE -pthread"/>
  <configure name="CXX" value="g++"/>
  <configure name="DEFS" value="-DHAVE_CONFIG_H"/>
  <configure name="DELEGATES" value="bzlib mpeg jbig jng jpeg lcms png tiff xml zlib"/>
  <configure name="DISTCHECK_CONFIG_FLAGS" value="'CFLAGS=-L.' 'LIBS=-ljbig -ltiff -ljasper -ljpeg -lpng -lbz2 -lz -lpthread -lm -lfreetype' --disable-deprecated --with-quantum-depth=16 --with-jemalloc=no --with-umem=no --with-autotrace=no --with-gslib=no --with-fontpath= --with-gvc=no --with-rsvg=no --with-wmf=no --with-perl=no"/>
  <configure name="DOCUMENTATION_PATH" value=""/>
  <configure name="EXEC-PREFIX" value=""/>
  <configure name="EXECUTABLE_PATH" value="/"/>
  <configure name="FEATURES" value="DPC Zero-Configuration"/>
  <configure name="FILTER_PATH" value=""/>
  <configure name="HOST" value="x86_64-apple-darwin12.5.0"/>
  <configure name="INCLUDE_PATH" value=""/>
  <configure name="LDFLAGS" value="-L."/>
  <configure name="LIBRARY_PATH" value="."/>
  <configure name="LIBS" value="-ljbig -ltiff -ljasper -ljpeg -lpng -lbz2 -lz -lpthread -lm -lfreetype -ljbig -llcms2 -ltiff -ljpeg -lpng16 -lbz2 -lxml2 -lz -lm"/>
  <configure name="LIB_VERSION_NUMBER" value="6,9,0,0"/>
  <configure name="LIB_VERSION" value="0x690"/>
  <configure name="NAME" value="ImageMagick"/>
  <configure name="PCFLAGS" value="-DMAGICKCORE_HDRI_ENABLE=0 -DMAGICKCORE_QUANTUM_DEPTH=16"/>
  <configure name="PREFIX" value=""/>
  <configure name="QuantumDepth" value="16"/>
  <configure name="RELEASE_DATE" value="2014-12-17"/>
  <configure name="SHAREARCH_PATH" value=""/>
  <configure name="SHARE_PATH" value=""/>
  <configure name="SVN_REVISION" value="17068" />
  <configure name="TARGET_CPU" value="x86_64"/>
  <configure name="TARGET_OS" value="darwin12.5.0"/>
  <configure name="TARGET_VENDOR" value="apple"/>
  <configure name="VERSION" value="6.9.0"/>
  <configure name="WEBSITE" value="http://www.imagemagick.org"/>
</configuremap>
